pyms/__init__.py
pyms/constants.py
pyms/exceptions.py
pyms/__pycache__/__init__.cpython-36.pyc
pyms/__pycache__/__init__.cpython-37.pyc
pyms/__pycache__/constants.cpython-36.pyc
pyms/__pycache__/constants.cpython-37.pyc
pyms/__pycache__/exceptions.cpython-36.pyc
pyms/__pycache__/exceptions.cpython-37.pyc
pyms/cloud/aws/kms.py
pyms/cloud/aws/__pycache__/kms.cpython-36.pyc
pyms/cloud/aws/__pycache__/kms.cpython-37.pyc
pyms/cmd/__init__.py
pyms/cmd/main.py
pyms/cmd/__pycache__/__init__.cpython-36.pyc
pyms/cmd/__pycache__/__init__.cpython-37.pyc
pyms/cmd/__pycache__/main.cpython-36.pyc
pyms/cmd/__pycache__/main.cpython-37.pyc
pyms/config/__init__.py
pyms/config/conf.py
pyms/config/confile.py
pyms/config/resource.py
pyms/config/__pycache__/__init__.cpython-36.pyc
pyms/config/__pycache__/__init__.cpython-37.pyc
pyms/config/__pycache__/conf.cpython-36.pyc
pyms/config/__pycache__/conf.cpython-37.pyc
pyms/config/__pycache__/confile.cpython-36.pyc
pyms/config/__pycache__/confile.cpython-37.pyc
pyms/config/__pycache__/resource.cpython-36.pyc
pyms/config/__pycache__/resource.cpython-37.pyc
pyms/crypt/__init__.py
pyms/crypt/driver.py
pyms/crypt/fernet.py
pyms/crypt/__pycache__/__init__.cpython-36.pyc
pyms/crypt/__pycache__/__init__.cpython-37.pyc
pyms/crypt/__pycache__/driver.cpython-36.pyc
pyms/crypt/__pycache__/driver.cpython-37.pyc
pyms/crypt/__pycache__/fernet.cpython-36.pyc
pyms/crypt/__pycache__/fernet.cpython-37.pyc
pyms/flask/__init__.py
pyms/flask/__pycache__/__init__.cpython-36.pyc
pyms/flask/__pycache__/__init__.cpython-37.pyc
pyms/flask/app/__init__.py
pyms/flask/app/create_app.py
pyms/flask/app/create_config.py
pyms/flask/app/utils.py
pyms/flask/app/__pycache__/__init__.cpython-36.pyc
pyms/flask/app/__pycache__/__init__.cpython-37.pyc
pyms/flask/app/__pycache__/create_app.cpython-36.pyc
pyms/flask/app/__pycache__/create_app.cpython-37.pyc
pyms/flask/app/__pycache__/create_config.cpython-36.pyc
pyms/flask/app/__pycache__/create_config.cpython-37.pyc
py_ms-2.8.0.dist-info/AUTHORS
py_ms-2.8.0.dist-info/LICENSE
py_ms-2.8.0.dist-info/METADATA
py_ms-2.8.0.dist-info/WHEEL
py_ms-2.8.0.dist-info/entry_points.txt
py_ms-2.8.0.dist-info/top_level.txt
py_ms-2.8.0.dist-info/zip-safe
py_ms-2.8.0.dist-info/RECORD
